superpacman/__init__.py
superpacman/animation.py
superpacman/constants.py
superpacman/entity.py
superpacman/fruit.py
superpacman/ghosts.py
superpacman/junk.py
superpacman/mazedata.py
superpacman/modes.py
superpacman/nodes.py
superpacman/pacman.py
superpacman/pauser.py
superpacman/pellets.py
superpacman/run.py
superpacman/sprites.py
superpacman/text.py
superpacman/vector.py
superpacman-0.1.0.dist-info/LICENSE
superpacman-0.1.0.dist-info/METADATA
superpacman-0.1.0.dist-info/WHEEL
superpacman-0.1.0.dist-info/top_level.txt
superpacman-0.1.0.dist-info/RECORD
