Metadata-Version: 2.1
Name: superpacman
Version: 0.1.0
Summary: A sample Python package
Home-page: 
Author: 
Author-email: 
License: MIT
Classifier: Programming Language :: Python :: 3
Classifier: License :: OSI Approved :: MIT License
Classifier: Operating System :: OS Independent
License-File: LICENSE
Requires-Dist: numpy
Requires-Dist: pygame
